{"neighbours": {"e": "-0.55_51.6838", "sw": "-0.4393_51.4624", "ne": "-0.6607_51.6838", "n": "-0.6607_51.5731", "s": "-0.4393_51.5731", "w": "-0.55_51.4624", "x": "-0.55_51.5731", "se": "-0.4393_51.6838", "nw": "-0.6607_51.4624"}, "results": [{"description": "<p>Another day, another list. And who doesn't love a list which reveals Britain's grimiest hotels, as reviewed by real guests?</p>", "wgs84_lat": 51.54147217946911, "title": "The perfect place for a dirty weekend", "url": "", "rank": "", "wgs84_lon": -0.4456618388336298, "type": "guardian-article"}]}