{"neighbours": {"e": "loc_0.1142_51.7945", "sw": "loc_0.2249_51.5731", "ne": "loc_0.0035_51.7945", "n": "loc_0.0035_51.6838", "s": "loc_0.2249_51.6838", "w": "loc_0.1142_51.5731", "x": "loc_0.1142_51.6838", "se": "loc_0.2249_51.7945", "nw": "loc_0.0035_51.5731"}, "box_title": "Epping Forest 001A", "results": [{"description": "North Weald Bassett (locally known as North Weald) is a village and civil parish in the Epping Forest district of the county of Essex, England. It is located east of Epping, south-east of Chipping Ongar and south of Harlow (...)", "wgs84_lat": 51.7193, "title": "North Weald Bassett", "url": "http://en.wikipedia.org/wiki/North_Weald_Bassett", "rank": "", "wgs84_lon": 0.16284, "type": "wikipeida"}]}